{
    "songNames": {
        "AGoodFeelingBody": {"Name": "A Good Feeling Body", "LyricString": ""},
        "AlbionSongs": {"Name": "Albion Songs", "LyricString": ""},
        "ALetterFromTheFuture": {"Name": "A Letter From The Future", "LyricString": ""},
        "AllowanceIsEase": {"Name": "Allowance Is Ease", "LyricString": ""},
        "AllowTheFrequencyOfTheFullyManifestedMe": {"Name": "Allow The Frequency Of The Fully Manifested Me", "LyricString": ""},
        "AppearLotteryTimesComplete": {"Name": "Appear Lottery Times Complete", "LyricString": ""},
        "BeAllIn": {"Name": "Be All In", "LyricString": ""},
        "beautyHealing": {"Name": "Beauty Healing", "LyricString": ""},
        "BuildTheFire": {"Name": "Build The Fire", "LyricString": ""},
        "DemandingJoy": {"Name": "Demanding Joy", "LyricString": ""},
        "DominateTheLandScape": {"Name": "Dominate The Landscape", "LyricString": ""},
        "EveryCharkraInTheGrove": {"Name": "Every Chakra In The Grove", "LyricString": ""},
        "ForgeAFeelingDeep": {"Name": "Forge A Feeling Deep", "LyricString": ""},
        "FrequencyFlip": {"Name": "Frequency Flip", "LyricString": ""},
        "HealTimesComplete": {"Name": "Heal Times Complete", "LyricString": ""},
        "I'dRatherBeTheEngine": {"Name": "I'd Rather Be The Engine", "LyricString": ""},
        "I'mHereToSayItLoud&Clear": {"Name": "I'm Here To Say It Loud & Clear", "LyricString": ""},
        "IAmAwashInIt'sLight": {"Name": "I Am Awash In It's Light", "LyricString": ""},
        "ICodedTheMachine": {"Name": "I Coded The Machine", "LyricString": ""},
        "IgnitionOrbMeProgram": {"Name": "Ignition Orb", "LyricString": ""},
        "ILayedTheLines": {"Name": "I Laid The Lines", "LyricString": ""},
        "InstrumentalOnly": {"Name": "Instrumental Only", "LyricString": ""},
        "MybodyIsSohealthy": {"Name": "My Body Is So Healthy", "LyricString": ""},
        "MyTrueName": {"Name": "My True Name", "LyricString": ""},
        "OmManiPedehum": {"Name": "Om Mani Padme Hum", "LyricString": ""},
        "PureAwarenessIAM": {"Name": "Pure Awareness I AM", "LyricString": ""},
        "SmoothAsButter": {"Name": "Smooth As Butter", "LyricString": ""},
        "SwiftInTheEther": {"Name": "Swift In The Ether", "LyricString": ""},
        "TheCodeWritenBySoulPower": {"Name": "The Code Written By Soul Power", "LyricString": ""},
        "TheFullImersion": {"Name": "The Full Immersion", "LyricString": ""},
        "TheInsideOut": {"Name": "The Inside Out", "LyricString": ""},
        "TheMesTimesComplete": {"Name": "The Me's Times Complete", "LyricString": ""},
        "TheMesTimesInfinity": {"Name": "The Me's Times Infinity", "LyricString": ""},
        "TheUniversesMostExclusiveDoor": {"Name": "The Universes Most Exclusive Door", "LyricString": ""},
        "TheWorldOutsidesAStorm": {"Name": "The World Outside's A Storm", "LyricString": ""},
        "TrueScience": {"Name": "True Science", "LyricString": ""},
        "WokeUpThisMorningRap": {"Name": "Woke Up This Morning Rap", "LyricString": ""}
    }
}